mcp_server_qdrant/__init__.py
mcp_server_qdrant/document_ingest.py
mcp_server_qdrant/hosted_server.py
mcp_server_qdrant/main.py
mcp_server_qdrant/mcp_server.py
mcp_server_qdrant/memory.py
mcp_server_qdrant/qdrant.py
mcp_server_qdrant/server.py
mcp_server_qdrant/settings.py
mcp_server_qdrant/common/__init__.py
mcp_server_qdrant/common/filters.py
mcp_server_qdrant/common/func_tools.py
mcp_server_qdrant/common/telemetry.py
mcp_server_qdrant/common/wrap_filters.py
mcp_server_qdrant/embeddings/__init__.py
mcp_server_qdrant/embeddings/base.py
mcp_server_qdrant/embeddings/factory.py
mcp_server_qdrant/embeddings/fastembed.py
mcp_server_qdrant/embeddings/openai.py
mcp_server_qdrant/embeddings/types.py
mad_mcp_qdrant-1.4.0.dist-info/METADATA
mad_mcp_qdrant-1.4.0.dist-info/WHEEL
mad_mcp_qdrant-1.4.0.dist-info/entry_points.txt
mad_mcp_qdrant-1.4.0.dist-info/licenses/LICENSE
mad_mcp_qdrant-1.4.0.dist-info/RECORD
