Metadata-Version: 2.4
Name: mad-mcp-qdrant
Version: 1.4.0
Summary: MCP server for retrieving context from a Qdrant vector database
License-Expression: Apache-2.0
License-File: LICENSE
Requires-Python: >=3.10
Requires-Dist: fastembed>=0.6.0
Requires-Dist: fastmcp==2.7.0
Requires-Dist: openai>=1.40.0
Requires-Dist: pdf2image>=1.17.0
Requires-Dist: pydantic<2.12.0,>=2.10.6
Requires-Dist: pypdf>=4.2.0
Requires-Dist: pytesseract>=0.3.10
Requires-Dist: python-docx>=1.1.0
Requires-Dist: qdrant-client>=1.12.0
